pydojah/__init__.py
pydojah/dojah.py
pydojah/endpoints.py
py_dojah-1.0.1.dist-info/LICENSE
py_dojah-1.0.1.dist-info/METADATA
py_dojah-1.0.1.dist-info/WHEEL
py_dojah-1.0.1.dist-info/top_level.txt
py_dojah-1.0.1.dist-info/RECORD
