Metadata-Version: 2.1
Name: py-dojah
Version: 1.0.1
Summary: An API wrapper for dojah.io API
Home-page: https://github.com/Olamidun/py-dojah
Author: Kolapo Olamidun
Author-email: kolapoolamidun@gmail.com
License: UNKNOWN
Project-URL: Documentation, https://github.com/Olamidun/py-dojah/blob/master/README.md
Platform: UNKNOWN
Classifier: Programming Language :: Python :: 3
Classifier: License :: OSI Approved :: MIT License
Classifier: Operating System :: OS Independent
Requires-Python: >=3.6
Requires-Dist: requests
